scriptScraper/__init__.py
scriptScraper/extractors.py
scriptScraper/simpleScraper.py
scriptScraper/simpleSpider.py
script_scraper_alpha-0.0.6.dist-info/LICENSE
script_scraper_alpha-0.0.6.dist-info/METADATA
script_scraper_alpha-0.0.6.dist-info/WHEEL
script_scraper_alpha-0.0.6.dist-info/top_level.txt
script_scraper_alpha-0.0.6.dist-info/RECORD
