Metadata-Version: 2.1
Name: script-scraper-alpha
Version: 0.0.6
Summary: Provides a simple api interface with a scrapy backen for requesting complicated scraping tasks in an intuitive manner.
Home-page: https://github.com/vlad-yeghiazaryan/script-scraper
Author: Vladimir Yeghiazaryan
Author-email: vladimir.y2000@gmail.com
License: MIT License
Keywords: script scraper
Classifier: Framework :: Scrapy
Classifier: Programming Language :: Python :: 3
Requires-Python: >=3.7
License-File: LICENSE
Requires-Dist: Scrapy
Requires-Dist: scrapydo (==0.2.2)
